aetherpy/__init__.py
aetherpy/accel/__init__.py
aetherpy/accel/cupy_kernels.py
aetherpy/accel/numba_kernels.py
aetherpy/core/__init__.py
aetherpy/core/constrained.py
aetherpy/core/los.py
aetherpy/core/multiobserver.py
aetherpy/core/raycast.py
aetherpy/core/sweep.py
aetherpy/core/utils.py
aetherpy/data/__init__.py
aetherpy/data/loader.py
aetherpy/data/projection.py
aetherpy/data/pyramid.py
aetherpy/data/tiling.py
aetherpy/io/__init__.py
aetherpy/io/cli.py
aetherpy/io/plotting.py
aetherpy/io/raster.py
aetherpy/tests/__init__.py
aetherpy/tests/test_los.py
aetherpy/tests/test_multiobserver.py
aetherpy/tests/test_viewshed.py
aetherpy-1.0.0.dist-info/licenses/LICENSE.md
aetherpy-1.0.0.dist-info/METADATA
aetherpy-1.0.0.dist-info/WHEEL
aetherpy-1.0.0.dist-info/top_level.txt
aetherpy-1.0.0.dist-info/RECORD
