Metadata-Version: 2.4
Name: aetherpy
Version: 1.0.0
Summary: Fast Python library for terrain visibility analysis
Author-email: Lorenz Schmid <lorenzdschmid@gmail.com>
Project-URL: Homepage, https://github.com/SchmidL/aetherpy
Project-URL: Repository, https://github.com/SchmidL/aetherpy.git
Keywords: gis,viewshed,visibility,remote-sensing,dem
Classifier: Programming Language :: Python :: 3
Classifier: License :: OSI Approved :: MIT License
Classifier: Operating System :: OS Independent
Requires-Python: >=3.8
License-File: LICENSE.md
Requires-Dist: numpy>=1.20
Requires-Dist: numba>=0.55
Requires-Dist: rasterio>=1.2
Requires-Dist: matplotlib>=3.4
Requires-Dist: fiona>=1.8
Requires-Dist: joblib>=1.1
Dynamic: license-file
